git_annex_remote_googledrive/__init__.py
git_annex_remote_googledrive/__main__.py
git_annex_remote_googledrive/_version.py
git_annex_remote_googledrive/google_remote.py
git_annex_remote_googledrive/keys.py
git_annex_remote_googledrive/run.py
git_annex_remote_googledrive-1.3.2.dist-info/LICENSE
git_annex_remote_googledrive-1.3.2.dist-info/METADATA
git_annex_remote_googledrive-1.3.2.dist-info/WHEEL
git_annex_remote_googledrive-1.3.2.dist-info/entry_points.txt
git_annex_remote_googledrive-1.3.2.dist-info/top_level.txt
git_annex_remote_googledrive-1.3.2.dist-info/RECORD
