Metadata-Version: 2.1
Name: git-annex-remote-googledrive
Version: 1.3.2
Summary: git annex special remote for Google Drive
Home-page: https://github.com/Lykos153/git-annex-remote-googledrive
Author: Silvio Ankermann
Author-email: silvio@booq.org
License: GPLv3
Keywords: git-annex remote googledrive
Platform: UNKNOWN
Classifier: Development Status :: 4 - Beta
Classifier: Intended Audience :: Developers
Classifier: Topic :: Software Development :: Libraries
Classifier: License :: OSI Approved :: GNU General Public License v3 (GPLv3)
Classifier: Programming Language :: Python :: 3 :: Only
Classifier: Programming Language :: Python :: 3.4
Classifier: Programming Language :: Python :: 3.5
Classifier: Programming Language :: Python :: 3.6
License-File: LICENSE
Requires-Dist: annexremote
Requires-Dist: drivelib (>=0.1.4)
Requires-Dist: gitpython
Requires-Dist: tenacity
Requires-Dist: humanfriendly
